blanks_gen/__main__.py
blanks_gen/version.py
blanks_gen/resources/cell.tex
blanks_gen/resources/default_config.yaml
blanks_gen/resources/manual_cut_cell.tex
blanks_gen/resources/manual_cut_config.yaml
blanks_gen/resources/manual_cut_prefix.tex
blanks_gen/resources/postfix.tex
blanks_gen/resources/prefix.tex
blanks_gen-0.0.3.dist-info/METADATA
blanks_gen-0.0.3.dist-info/WHEEL
blanks_gen-0.0.3.dist-info/entry_points.txt
blanks_gen-0.0.3.dist-info/top_level.txt
blanks_gen-0.0.3.dist-info/RECORD
