Metadata-Version: 2.1
Name: blanks_gen
Version: 0.0.3
Summary: blanks_gen is a script that wraps tectonic to generate blanks for [Chgk](https://en.wikipedia.org/wiki/What%3F_Where%3F_When%3F)
Home-page: https://gitlab.com/peczony/blanks_gen
Author: Alexander Pecheny
Author-email: ap@pecheny.me
Classifier: Programming Language :: Python :: 3
Classifier: License :: OSI Approved :: MIT License
Classifier: Operating System :: OS Independent
Requires-Dist: pecheny-utils
Requires-Dist: pypdf
Requires-Dist: PyYAML
